<?xml version="1.0"?>
<!DOCTYPE hibernate-mapping PUBLIC "-//Hibernate/Hibernate Mapping DTD 3.0//EN"
                                   "http://hibernate.sourceforge.net/hibernate-mapping-3.0.dtd">
<!-- Generated 2011-11-25 20:37:54 by Hibernate Tools 3.4.0.CR1 -->
<hibernate-mapping package="com.rbs.model">
 <class name="com.rbs.model.Application" table="APPLICATION">
  <id access="field" name="aid" type="java.lang.String">
   <column name="AID"/>
   <generator class="assigned"/>
  </id>
  <property access="field" column="roomID" generated="never"
   lazy="false" name="roomID" type="int">
   <column name="ROOMID"/>
  </property>
  <property access="field" column="roomNum" generated="never"
   lazy="false" name="roomNum" type="int">
   <column name="ROOMNUM"/>
  </property>
  <property access="field" column="appName" generated="never"
   lazy="false" name="appName" type="java.lang.String">
   <column name="APPNAME"/>
  </property>
  <many-to-one access="field" class="com.rbs.model.TimeInterval"
   fetch="join" name="time">
   <column name="TIME"/>
  </many-to-one>
 </class>
</hibernate-mapping>
